Workbook

Sheet How to use
A1: TryoutHQ - Test Scenarios
A3: What this is | B3: One row per test case, generated from TEST_SCENARIOS.txt. The .txt stays the source of truth for the detailed wording.
A4: How to run | B4: 1) Run each "Before" case on the OLD build and write what you see in "Before result". 2) Run "After" and "Feature" cases on the NEW build and set Status. 3) Run every "Regression" case on the NEW build.
A5: Status values | B5: Pass / Fail / Blocked / N/A (drop-down). Fail rows turn red, Pass rows green.
A6: Phase | B6: Before = old-build baseline; After = expected result after a change; Feature = full-coverage suite (sections 25-50); Regression = safety net; General = setup/notes.
A7: Verified (sim) | B7: Yes = already seen working in the iOS simulator by the developer. It still needs your own run, and Android is not verified for any row.
A8: Tabs | B8: "All tests" = every case, filterable. "Summary" = live counts per section (formulas).
A9: Not built | B9: Section 19 (guardian shows under Team) is deferred; its rows are for the baseline only.
A10: Payments | B10: Use Stripe TEST mode only. Never test with a real card.

Sheet Summary
A1: Section | B1: Section title | C1: Total | D1: Pass | E1: Fail | F1: Blocked | G1: N/A | H1: Not run | I1: % done
A2: 1 | B2: LOG OUT / DELETE ACCOUNT BLOCKED AT THE BOTTOM (Android) | C2: =COUNTIF('All tests'!$A:$A,A2) | D2: =COUNTIFS('All tests'!$A:$A,$A2,'All tests'!$I:$I,"Pass") | E2: =COUNTIFS('All tests'!$A:$A,$A2,'All tests'!$I:$I,"Fail") | F2: =COUNTIFS('All tests'!$A:$A,$A2,'All tests'!$I:$I,"Blocked") | G2: =COUNTIFS('All tests'!$A:$A,$A2,'All tests'!$I:$I,"N/A") | H2: =C2-SUM(D2:G2) | I2: =IF(C2=0,0,SUM(D2:G2)/C2)
A3: 2 | B3: EXCEL (.xlsx) IMPORT ONLY IMPORTS ONE NAME | C3: =COUNTIF('All tests'!$A:$A,A3) | D3: =COUNTIFS('All tests'!$A:$A,$A3,'All tests'!$I:$I,"Pass") | E3: =COUNTIFS('All tests'!$A:$A,$A3,'All tests'!$I:$I,"Fail") | F3: =COUNTIFS('All tests'!$A:$A,$A3,'All tests'!$I:$I,"Blocked") | G3: =COUNTIFS('All tests'!$A:$A,$A3,'All tests'!$I:$I,"N/A") | H3: =C3-SUM(D3:G3) | I3: =IF(C3=0,0,SUM(D3:G3)/C3)
A4: 3 | B4: CSV / EXCEL IMPORT IS SLOW (20 NAMES) | C4: =COUNTIF('All tests'!$A:$A,A4) | D4: =COUNTIFS('All tests'!$A:$A,$A4,'All tests'!$I:$I,"Pass") | E4: =COUNTIFS('All tests'!$A:$A,$A4,'All tests'!$I:$I,"Fail") | F4: =COUNTIFS('All tests'!$A:$A,$A4,'All tests'!$I:$I,"Blocked") | G4: =COUNTIFS('All tests'!$A:$A,$A4,'All tests'!$I:$I,"N/A") | H4: =C4-SUM(D4:G4) | I4: =IF(C4=0,0,SUM(D4:G4)/C4)
A5: 4 | B5: REGISTRATIONS: SELECT MULTIPLE, "ADD" ONLY SENDS ONE PLAYER (HIGH) | C5: =COUNTIF('All tests'!$A:$A,A5) | D5: =COUNTIFS('All tests'!$A:$A,$A5,'All tests'!$I:$I,"Pass") | E5: =COUNTIFS('All tests'!$A:$A,$A5,'All tests'!$I:$I,"Fail") | F5: =COUNTIFS('All tests'!$A:$A,$A5,'All tests'!$I:$I,"Blocked") | G5: =COUNTIFS('All tests'!$A:$A,$A5,'All tests'!$I:$I,"N/A") | H5: =C5-SUM(D5:G5) | I5: =IF(C5=0,0,SUM(D5:G5)/C5)
A6: 5 | B6: SELECT ALL PLAYERS ON A ROSTER AND DELETE (HIGH) | C6: =COUNTIF('All tests'!$A:$A,A6) | D6: =COUNTIFS('All tests'!$A:$A,$A6,'All tests'!$I:$I,"Pass") | E6: =COUNTIFS('All tests'!$A:$A,$A6,'All tests'!$I:$I,"Fail") | F6: =COUNTIFS('All tests'!$A:$A,$A6,'All tests'!$I:$I,"Blocked") | G6: =COUNTIFS('All tests'!$A:$A,$A6,'All tests'!$I:$I,"N/A") | H6: =C6-SUM(D6:G6) | I6: =IF(C6=0,0,SUM(D6:G6)/C6)
A7: 6 | B7: EDIT BUTTON ON THE EVALUATION TILE | C7: =COUNTIF('All tests'!$A:$A,A7) | D7: =COUNTIFS('All tests'!$A:$A,$A7,'All tests'!$I:$I,"Pass") | E7: =COUNTIFS('All tests'!$A:$A,$A7,'All tests'!$I:$I,"Fail") | F7: =COUNTIFS('All tests'!$A:$A,$A7,'All tests'!$I:$I,"Blocked") | G7: =COUNTIFS('All tests'!$A:$A,$A7,'All tests'!$I:$I,"N/A") | H7: =C7-SUM(D7:G7) | I7: =IF(C7=0,0,SUM(D7:G7)/C7)
A8: 7 | B8: DATA / PERMISSION CHECKS (touching several fixes) | C8: =COUNTIF('All tests'!$A:$A,A8) | D8: =COUNTIFS('All tests'!$A:$A,$A8,'All tests'!$I:$I,"Pass") | E8: =COUNTIFS('All tests'!$A:$A,$A8,'All tests'!$I:$I,"Fail") | F8: =COUNTIFS('All tests'!$A:$A,$A8,'All tests'!$I:$I,"Blocked") | G8: =COUNTIFS('All tests'!$A:$A,$A8,'All tests'!$I:$I,"N/A") | H8: =C8-SUM(D8:G8) | I8: =IF(C8=0,0,SUM(D8:G8)/C8)
A9: 8 | B9: REGRESSION CHECKLIST (run on the NEW build) | C9: =COUNTIF('All tests'!$A:$A,A9) | D9: =COUNTIFS('All tests'!$A:$A,$A9,'All tests'!$I:$I,"Pass") | E9: =COUNTIFS('All tests'!$A:$A,$A9,'All tests'!$I:$I,"Fail") | F9: =COUNTIFS('All tests'!$A:$A,$A9,'All tests'!$I:$I,"Blocked") | G9: =COUNTIFS('All tests'!$A:$A,$A9,'All tests'!$I:$I,"N/A") | H9: =C9-SUM(D9:G9) | I9: =IF(C9=0,0,SUM(D9:G9)/C9)
A10: 10 | B10: EVALUATION SHOWS ON THE WRONG PLACES (team vs standalone) (HIGH) | C10: =COUNTIF('All tests'!$A:$A,A10) | D10: =COUNTIFS('All tests'!$A:$A,$A10,'All tests'!$I:$I,"Pass") | E10: =COUNTIFS('All tests'!$A:$A,$A10,'All tests'!$I:$I,"Fail") | F10: =COUNTIFS('All tests'!$A:$A,$A10,'All tests'!$I:$I,"Blocked") | G10: =COUNTIFS('All tests'!$A:$A,$A10,'All tests'!$I:$I,"N/A") | H10: =C10-SUM(D10:G10) | I10: =IF(C10=0,0,SUM(D10:G10)/C10)
A11: 11 | B11: DRAG AND DROP / TRADE PLAYERS BETWEEN TEAMS ON THE APK (HIGH) | C11: =COUNTIF('All tests'!$A:$A,A11) | D11: =COUNTIFS('All tests'!$A:$A,$A11,'All tests'!$I:$I,"Pass") | E11: =COUNTIFS('All tests'!$A:$A,$A11,'All tests'!$I:$I,"Fail") | F11: =COUNTIFS('All tests'!$A:$A,$A11,'All tests'!$I:$I,"Blocked") | G11: =COUNTIFS('All tests'!$A:$A,$A11,'All tests'!$I:$I,"N/A") | H11: =C11-SUM(D11:G11) | I11: =IF(C11=0,0,SUM(D11:G11)/C11)
A12: 12 | B12: EXTRA REGRESSION CHECKS FOR SECTIONS 10 AND 11 | C12: =COUNTIF('All tests'!$A:$A,A12) | D12: =COUNTIFS('All tests'!$A:$A,$A12,'All tests'!$I:$I,"Pass") | E12: =COUNTIFS('All tests'!$A:$A,$A12,'All tests'!$I:$I,"Fail") | F12: =COUNTIFS('All tests'!$A:$A,$A12,'All tests'!$I:$I,"Blocked") | G12: =COUNTIFS('All tests'!$A:$A,$A12,'All tests'!$I:$I,"N/A") | H12: =C12-SUM(D12:G12) | I12: =IF(C12=0,0,SUM(D12:G12)/C12)
A13: 13 | B13: TEAM SCREEN TITLE: "<TEAM NAME> HUB" | C13: =COUNTIF('All tests'!$A:$A,A13) | D13: =COUNTIFS('All tests'!$A:$A,$A13,'All tests'!$I:$I,"Pass") | E13: =COUNTIFS('All tests'!$A:$A,$A13,'All tests'!$I:$I,"Fail") | F13: =COUNTIFS('All tests'!$A:$A,$A13,'All tests'!$I:$I,"Blocked") | G13: =COUNTIFS('All tests'!$A:$A,$A13,'All tests'!$I:$I,"N/A") | H13: =C13-SUM(D13:G13) | I13: =IF(C13=0,0,SUM(D13:G13)/C13)
... A51: 51 | B51: WEB APP PARITY (branch feat/shawn-feedback-web-parity) | C51: =COUNTIF('All tests'!$A:$A,A51) | D51: =COUNTIFS('All tests'!$A:$A,$A51,'All tests'!$I:$I,"Pass") | E51: =COUNTIFS('All tests'!$A:$A,$A51,'All tests'!$I:$I,"Fail") | F51: =COUNTIFS('All tests'!$A:$A,$A51,'All tests'!$I:$I,"Blocked") | G51: =COUNTIFS('All tests'!$A:$A,$A51,'All tests'!$I:$I,"N/A") | H51: =C51-SUM(D51:G51) | I51: =IF(C51=0,0,SUM(D51:G51)/C51)
B52: TOTAL | C52: =SUM(C2:C51) | D52: =SUM(D2:D51) | E52: =SUM(E2:E51) | F52: =SUM(F2:F51) | G52: =SUM(G2:G51) | H52: =SUM(H2:H51) | I52: =IF(C52=0,0,SUM(D52:G52)/C52)

Sheet All tests
A1: Section | B1: Section title | C1: ID | D1: Phase | E1: Group | F1: Test case | G1: Verified (sim) | H1: Before result | I1: Status | J1: Actual result / notes | K1: Tester | L1: Date | M1: Bug link
A2: 1 | B2: LOG OUT / DELETE ACCOUNT BLOCKED AT THE BOTTOM (Android) | C2: 1.1 | D2: Before | E2: BEFORE | F2: Android, 3-button nav. Profile > scroll to very bottom. Expected (bug): "Log Out" is partly/fully hidden by the nav bar.
A3: 1 | B3: LOG OUT / DELETE ACCOUNT BLOCKED AT THE BOTTOM (Android) | C3: 1.2 | D3: Before | E3: BEFORE | F3: Try to tap the bottom edge of Log Out and Delete Account. Expected (bug): bottom edge is not tappable.
A4: 1 | B4: LOG OUT / DELETE ACCOUNT BLOCKED AT THE BOTTOM (Android) | C4: 1.3 | D4: After | E4: AFTER (expected) | F4: Android 3-button nav: Log Out fully visible with clear space below it, fully tappable.
A5: 1 | B5: LOG OUT / DELETE ACCOUNT BLOCKED AT THE BOTTOM (Android) | C5: 1.4 | D5: After | E5: AFTER (expected) | F5: Android gesture nav: no large empty band at the bottom.
A6: 1 | B6: LOG OUT / DELETE ACCOUNT BLOCKED AT THE BOTTOM (Android) | C6: 1.5 | D6: After | E6: AFTER (expected) | F6: Android 13/14 (no forced edge-to-edge): NO extra blank space added.
A7: 1 | B7: LOG OUT / DELETE ACCOUNT BLOCKED AT THE BOTTOM (Android) | C7: 1.6 | D7: After | E7: AFTER (expected) | F7: Font size 130-200%: Delete Account and Log Out still reachable.
A8: 1 | B8: LOG OUT / DELETE ACCOUNT BLOCKED AT THE BOTTOM (Android) | C8: 1.7 | D8: After | E8: AFTER (expected) | F8: Landscape: nothing hidden behind the side nav bar.
A9: 1 | B9: LOG OUT / DELETE ACCOUNT BLOCKED AT THE BOTTOM (Android) | C9: 1.8 | D9: After | E9: AFTER (expected) | F9: Guardian-only account (some cards hidden): Danger Zone and Log Out still reachable.
A10: 1 | B10: LOG OUT / DELETE ACCOUNT BLOCKED AT THE BOTTOM (Android) | C10: 1.9 | D10: After | E10: AFTER (expected) | F10: Delete Account: dialog appears; Cancel keeps you signed in.
A11: 1 | B11: LOG OUT / DELETE ACCOUNT BLOCKED AT THE BOTTOM (Android) | C11: 1.10 | D11: After | E11: AFTER (expected) | F11: Log Out: shows loading state, ends on login screen.
A12: 1 | B12: LOG OUT / DELETE ACCOUNT BLOCKED AT THE BOTTOM (Android) | C12: 1.11 | D12: After | E12: AFTER (expected) | F12: iPhone: Profile looks unchanged (no new gap).
A13: 1 | B13: LOG OUT / DELETE ACCOUNT BLOCKED AT THE BOTTOM (Android) | C13: 1.12 | D13: After | E13: AFTER (expected) | F13: Other long scroll screens (season settings, team settings, forms ending in Save): last button fully visible, no double padding.
... A47: 4 | B47: REGISTRATIONS: SELECT MULTIPLE, "ADD" ONLY SENDS ONE PLAYER (HIGH) | C47: 4.2 | D47: Before | E47: BEFORE | F47: Tap "Add to Roster" on one of the selected cards, pick a team. Expected (bug): only that ONE player is added.
A48: 4 | B48: REGISTRATIONS: SELECT MULTIPLE, "ADD" ONLY SENDS ONE PLAYER (HIGH) | C48: 4.3 | D48: After | E48: AFTER (expected) | F48: Tick 2 players. Ticked cards read "Add 2 to Roster"; unticked cards still read "Add to Roster". A bar at the bottom shows "2 selected [Clear] [Add 2 to Roster]" and stays visible while scrolling. | G48: Yes
A49: 4 | B49: REGISTRATIONS: SELECT MULTIPLE, "ADD" ONLY SENDS ONE PLAYER (HIGH) | C49: 4.4 | D49: After | E49: AFTER (expected) | F49: Tap the card's "Add 2 to Roster" -> dialog title "Add 2 Players". | G49: Yes
A50: 4 | B50: REGISTRATIONS: SELECT MULTIPLE, "ADD" ONLY SENDS ONE PLAYER (HIGH) | C50: 4.5 | D50: After | E50: AFTER (expected) | F50: Confirm to a TEAM: both players appear on the team roster; team Players badge +2 without a manual refresh.
A51: 4 | B51: REGISTRATIONS: SELECT MULTIPLE, "ADD" ONLY SENDS ONE PLAYER (HIGH) | C51: 4.6 | D51: After | E51: AFTER (expected) | F51: Confirm to an EVALUATION: both appear on that roster.
A52: 4 | B52: REGISTRATIONS: SELECT MULTIPLE, "ADD" ONLY SENDS ONE PLAYER (HIGH) | C52: 4.7 | D52: After | E52: AFTER (expected) | F52: Select All (25) -> add to Team: all 25 land; progress bar reaches 25 of 25; DB team_roster count +25.
A53: 4 | B53: REGISTRATIONS: SELECT MULTIPLE, "ADD" ONLY SENDS ONE PLAYER (HIGH) | C53: 4.8 | D53: After | E53: AFTER (expected) | F53: Same with destination Evaluation: +25.
A54: 4 | B54: REGISTRATIONS: SELECT MULTIPLE, "ADD" ONLY SENDS ONE PLAYER (HIGH) | C54: 4.9 | D54: After | E54: AFTER (expected) | F54: Two siblings (same guardian email) ticked -> both added.
A55: 4 | B55: REGISTRATIONS: SELECT MULTIPLE, "ADD" ONLY SENDS ONE PLAYER (HIGH) | C55: 4.10 | D55: After | E55: AFTER (expected) | F55: Tick a player, DISMISS them, then add: count and result exclude the dismissed player.
A56: 4 | B56: REGISTRATIONS: SELECT MULTIPLE, "ADD" ONLY SENDS ONE PLAYER (HIGH) | C56: 4.11 | D56: After | E56: AFTER (expected) | F56: Tap "Add to Roster" on an UNTICKED card while others are ticked -> adds only that one player (explicit choice).
A57: 4 | B57: REGISTRATIONS: SELECT MULTIPLE, "ADD" ONLY SENDS ONE PLAYER (HIGH) | C57: 4.12 | D57: After | E57: AFTER (expected) | F57: Single player, no selection: "Add to Roster" works as before.
A58: 4 | B58: REGISTRATIONS: SELECT MULTIPLE, "ADD" ONLY SENDS ONE PLAYER (HIGH) | C58: 4.13 | D58: After | E58: AFTER (expected) | F58: Registration profile popup > "Add to Roster" -> adds that one.
A59: 4 | B59: REGISTRATIONS: SELECT MULTIPLE, "ADD" ONLY SENDS ONE PLAYER (HIGH) | C59: 4.14 | D59: After | E59: AFTER (expected) | F59: Free-plan player limit: adding past the limit shows the limit message; nothing partially added.
A60: 4 | B60: REGISTRATIONS: SELECT MULTIPLE, "ADD" ONLY SENDS ONE PLAYER (HIGH) | C60: 4.15 | D60: After | E60: AFTER (expected) | F60: "Clear" empties the selection and hides the bar.
A61: 4 | B61: REGISTRATIONS: SELECT MULTIPLE, "ADD" ONLY SENDS ONE PLAYER (HIGH) | C61: 4.16 | D61: After | E61: AFTER (expected) | F61: Switch to the "All" / "Dismissed" tab -> bar is hidden.
... A65: 5 | B65: SELECT ALL PLAYERS ON A ROSTER AND DELETE (HIGH) | C65: 5.2 | D65: After | E65: AFTER (expected) | F65: "Select" button appears (only when the team has players).
A66: 5 | B66: SELECT ALL PLAYERS ON A ROSTER AND DELETE (HIGH) | C66: 5.3 | D66: After | E66: AFTER (expected) | F66: Tap Select -> Back / Select All / Delete Selected (disabled), checkboxes on every row, per-row Remove hidden. | G66: Yes
A67: 5 | B67: SELECT ALL PLAYERS ON A ROSTER AND DELETE (HIGH) | C67: 5.4 | D67: After | E67: AFTER (expected) | F67: Select All with NO search -> "Delete Selected (N)" where N is the WHOLE team (999 on the test team), not just loaded rows. | G67: Yes
A68: 5 | B68: SELECT ALL PLAYERS ON A ROSTER AND DELETE (HIGH) | C68: 5.5 | D68: After | E68: AFTER (expected) | F68: Tap Delete Selected -> confirmation shows the right count.
A69: 5 | B69: SELECT ALL PLAYERS ON A ROSTER AND DELETE (HIGH) | C69: 5.6 | D69: After | E69: AFTER (expected) | F69: Confirm -> all removed; list empties; Players badge 0; no page refresh needed; DB team_roster rows gone.
A70: 5 | B70: SELECT ALL PLAYERS ON A ROSTER AND DELETE (HIGH) | C70: 5.7 | D70: After | E70: AFTER (expected) | F70: Tap individual rows to select 3, delete -> only those 3 go.
A71: 5 | B71: SELECT ALL PLAYERS ON A ROSTER AND DELETE (HIGH) | C71: 5.8 | D71: After | E71: AFTER (expected) | F71: Search "Smith" then Select All -> selects only the matches shown; deleting removes only those.
A72: 5 | B72: SELECT ALL PLAYERS ON A ROSTER AND DELETE (HIGH) | C72: 5.9 | D72: After | E72: AFTER (expected) | F72: Deselect All returns count to 0 and disables Delete.
A73: 5 | B73: SELECT ALL PLAYERS ON A ROSTER AND DELETE (HIGH) | C73: 5.10 | D73: After | E73: AFTER (expected) | F73: Back exits select mode with nothing deleted.
A74: 5 | B74: SELECT ALL PLAYERS ON A ROSTER AND DELETE (HIGH) | C74: 5.11 | D74: After | E74: AFTER (expected) | F74: Switch tab (Schedule/Evaluations) while in select mode, then return -> select mode is off, nothing selected.
A75: 5 | B75: SELECT ALL PLAYERS ON A ROSTER AND DELETE (HIGH) | C75: 5.12 | D75: After | E75: AFTER (expected) | F75: Airplane mode during delete -> error message; players still shown match what is really on the roster after refresh.
A76: 5 | B76: SELECT ALL PLAYERS ON A ROSTER AND DELETE (HIGH) | C76: 5.13 | D76: After | E76: AFTER (expected) | F76: Delete everyone, then add one player again -> works, empty state shown in between.
A77: 5 | B77: SELECT ALL PLAYERS ON A ROSTER AND DELETE (HIGH) | C77: 5.14 | D77: After | E77: AFTER (expected) | F77: Old single "Remove" (outside select mode) still works with its confirmation.
A78: 5 | B78: SELECT ALL PLAYERS ON A ROSTER AND DELETE (HIGH) | C78: 5.15 | D78: After | E78: AFTER (expected) | F78: Athletes are NOT erased from the account: after removing from the team they can be added again via "Add Players from Evaluations".
A79: 5 | B79: SELECT ALL PLAYERS ON A ROSTER AND DELETE (HIGH) | C79: 5.16 | D79: After | E79: AFTER (expected) | F79: Season/schedule screens (RSVP counts) refresh after removal.
... A87: 6 | B87: EDIT BUTTON ON THE EVALUATION TILE | C87: 6.2 | D87: Before | E87: BEFORE | F87: To edit, open evaluation > Settings tab > "Edit Details".
A88: 6 | B88: EDIT BUTTON ON THE EVALUATION TILE | C88: 6.3 | D88: After | E88: AFTER (expected) | F88: A pencil icon sits next to the trash icon on every evaluation tile. | G88: Yes
A89: 6 | B89: EDIT BUTTON ON THE EVALUATION TILE | C89: 6.4 | D89: After | E89: AFTER (expected) | F89: Tap pencil -> "Edit Evaluation" dialog pre-filled with name, date, start time, END time and location. | G89: Yes
A90: 6 | B90: EDIT BUTTON ON THE EVALUATION TILE | C90: 6.5 | D90: After | E90: AFTER (expected) | F90: Change the name + location, Save -> tile updates immediately; opening the evaluation > Settings shows the same values.
A91: 6 | B91: EDIT BUTTON ON THE EVALUATION TILE | C91: 6.6 | D91: After | E91: AFTER (expected) | F91: Pencil > Close/X without saving -> nothing changes.
A92: 6 | B92: EDIT BUTTON ON THE EVALUATION TILE | C92: 6.7 | D92: After | E92: AFTER (expected) | F92: Tap the tile body -> still opens the evaluation. | G92: Yes
A93: 6 | B93: EDIT BUTTON ON THE EVALUATION TILE | C93: 6.8 | D93: After | E93: AFTER (expected) | F93: Tap trash -> delete confirmation still works (cancel it).
A94: 6 | B94: EDIT BUTTON ON THE EVALUATION TILE | C94: 6.9 | D94: After | E94: AFTER (expected) | F94: Open pencil on tile A, close, open on tile B -> dialog shows B's values (no leftovers from A).
A95: 6 | B95: EDIT BUTTON ON THE EVALUATION TILE | C95: 6.10 | D95: After | E95: AFTER (expected) | F95: Airplane mode + Save -> error alert, dialog stays open.
A96: 6 | B96: EDIT BUTTON ON THE EVALUATION TILE | C96: 6.11 | D96: After | E96: AFTER (expected) | F96: Combine Mode on: tapping tiles still selects for combine; pencil does not break combine selection.
A97: 6 | B97: EDIT BUTTON ON THE EVALUATION TILE | C97: 6.12 | D97: After | E97: AFTER (expected) | F97: Pencil/trash tap targets are comfortable on a small phone (no mis-taps between them).
A98: 6 | B98: EDIT BUTTON ON THE EVALUATION TILE | C98: 6.13 | D98: After | E98: AFTER (expected) | F98: Evaluation Settings > "Edit Details" (old route) still works and shows updated values.
A99: 6 | B99: EDIT BUTTON ON THE EVALUATION TILE | C99: 6.14 | D99: After | E99: AFTER (expected) | F99: The "Assigned to me" tiles (evaluations where you are only the assessor) - confirm with Shawn whether they need an edit button; currently they do NOT have one.
A100: 7 | B100: DATA / PERMISSION CHECKS (touching several fixes) | C100: 7.1 | D100: General | F100: Owner coach account: all sections above work.
A101: 7 | B101: DATA / PERMISSION CHECKS (touching several fixes) | C101: 7.2 | D101: General | F101: Delegated club manager on a club team: add, remove, import, select-all-delete all work and respect permissions.
A102: 7 | B102: DATA / PERMISSION CHECKS (touching several fixes) | C102: 7.3 | D102: General | F102: Assessor-only account: cannot see edit/delete controls they could not before.
A103: 7 | B103: DATA / PERMISSION CHECKS (touching several fixes) | C103: 7.4 | D103: General | F103: Guardian account: no new controls appear.
A104: 7 | B104: DATA / PERMISSION CHECKS (touching several fixes) | C104: 7.5 | D104: General | F104: Player limit on Free plan enforced for: single add, bulk add from registrations, import.
A105: 7 | B105: DATA / PERMISSION CHECKS (touching several fixes) | C105: 7.6 | D105: General | F105: Row-level security: removing players you do not own is refused with a clear message (not a silent success).
A106: 8 | B106: REGRESSION CHECKLIST (run on the NEW build) | C106: 8.1 | D106: Regression | E106: IMPORT / ROSTER WRITES | F106: "+ Add Player Manually" on a team still works.
A107: 8 | B107: REGRESSION CHECKLIST (run on the NEW build) | C107: 8.2 | D107: Regression | E107: IMPORT / ROSTER WRITES | F107: Add Players from Evaluations (tap-select + Select all) still adds the right players, sends invites.
A108: 8 | B108: REGRESSION CHECKLIST (run on the NEW build) | C108: 8.3 | D108: Regression | E108: IMPORT / ROSTER WRITES | F108: Per-row Remove on the team roster still works.
A109: 8 | B109: REGRESSION CHECKLIST (run on the NEW build) | C109: 8.4 | D109: Regression | E109: IMPORT / ROSTER WRITES | F109: Evaluation roster: Add, Import, Select, Tools all work.
A110: 8 | B110: REGRESSION CHECKLIST (run on the NEW build) | C110: 8.5 | D110: Regression | E110: IMPORT / ROSTER WRITES | F110: Jersey and position values saved correctly after import.
A111: 8 | B111: REGRESSION CHECKLIST (run on the NEW build) | C111: 8.6 | D111: Regression | E111: IMPORT / ROSTER WRITES | F111: Season roster sync: a player added to a team with a season shows in that season's roster / RSVP list.
A112: 8 | B112: REGRESSION CHECKLIST (run on the NEW build) | C112: 8.7 | D112: Regression | E112: IMPORT / ROSTER WRITES | F112: Portal invites: sent once, no duplicates, none to players already on the roster.
A113: 8 | B113: REGRESSION CHECKLIST (run on the NEW build) | C113: 8.8 | D113: Regression | E113: REGISTRATIONS | F113: Dismiss a registration; Simulate QR Reg; Export CSV; Show QR; Share.
A114: 8 | B114: REGRESSION CHECKLIST (run on the NEW build) | C114: 8.9 | D114: Regression | E114: REGISTRATIONS | F114: Dummy Data / Clear Dummy Data still work.
A115: 8 | B115: REGRESSION CHECKLIST (run on the NEW build) | C115: 8.10 | D115: Regression | E115: REGISTRATIONS | F115: Tabs Pending / All / Dismissed switch correctly and the Pending badge is accurate.
A116: 8 | B116: REGRESSION CHECKLIST (run on the NEW build) | C116: 8.11 | D116: Regression | E116: CACHES / REFRESH | F116: After any add/delete: team roster, player count badge, dashboard evaluation count, Regs badge all update without pull-to-refresh.
A117: 8 | B117: REGRESSION CHECKLIST (run on the NEW build) | C117: 8.12 | D117: Regression | E117: CACHES / REFRESH | F117: The friend-package picker / Team Builder still opens and lists the roster correctly after roster changes.
... A137: 10 | B137: EVALUATION SHOWS ON THE WRONG PLACES (team vs standalone) (HIGH) | C137: 10.8 | D137: After | E137: AFTER (expected) | F137: Create a new team after that: team Evaluations tab is EMPTY ("No evaluations linked"), badge 0.
A138: 10 | B138: EVALUATION SHOWS ON THE WRONG PLACES (team vs standalone) (HIGH) | C138: 10.9 | D138: After | E138: AFTER (expected) | F138: Evaluation created from a team (Create button): appears on that team's tab, badge +1; does NOT appear in the home list. (Team-linked "Hello" gone from home, still on its team: verified in simulator; creating a NEW one not yet run.) | G138: Yes
A139: 10 | B139: EVALUATION SHOWS ON THE WRONG PLACES (team vs standalone) (HIGH) | C139: 10.10 | D139: After | E139: AFTER (expected) | F139: Evaluation created with the Team chip: same as 10.9.
A140: 10 | B140: EVALUATION SHOWS ON THE WRONG PLACES (team vs standalone) (HIGH) | C140: 10.11 | D140: After | E140: AFTER (expected) | F140: Two teams A and B: evaluation for A shows only on A, never on B.
A141: 10 | B141: EVALUATION SHOWS ON THE WRONG PLACES (team vs standalone) (HIGH) | C141: 10.12 | D141: After | E141: AFTER (expected) | F141: "Attach Existing" on team A: pick a standalone evaluation -> it appears on A and disappears from the home list.
A142: 10 | B142: EVALUATION SHOWS ON THE WRONG PLACES (team vs standalone) (HIGH) | C142: 10.13 | D142: After | E142: AFTER (expected) | F142: Attach Existing modal lists ONLY standalone evaluations (not ones already on another team).
A143: 10 | B143: EVALUATION SHOWS ON THE WRONG PLACES (team vs standalone) (HIGH) | C143: 10.14 | D143: After | E143: AFTER (expected) | F143: Home "Evaluations" tile count equals the number of rows in the home list (standalone only). | G143: Yes
A144: 10 | B144: EVALUATION SHOWS ON THE WRONG PLACES (team vs standalone) (HIGH) | C144: 10.15 | D144: After | E144: AFTER (expected) | F144: Open a team-linked evaluation from the team tab: opens normally (roster, regs, results, settings all work). (opened + Results verified in simulator) | G144: Yes
A145: 10 | B145: EVALUATION SHOWS ON THE WRONG PLACES (team vs standalone) (HIGH) | C145: 10.16 | D145: After | E145: AFTER (expected) | F145: Edit pencil (new tile edit) still works for standalone tiles.
A146: 10 | B146: EVALUATION SHOWS ON THE WRONG PLACES (team vs standalone) (HIGH) | C146: 10.17 | D146: After | E146: AFTER (expected) | F146: Empty state: if every evaluation is team-linked, home list shows the "No evaluations yet" empty state, not a blank screen. | G146: Yes
A147: 10 | B147: EVALUATION SHOWS ON THE WRONG PLACES (team vs standalone) (HIGH) | C147: 10.18 | D147: After | E147: AFTER (expected) | F147: Team Builder / Results / Export for a team-linked evaluation still reachable from the team's tab.
A148: 10 | B148: EVALUATION SHOWS ON THE WRONG PLACES (team vs standalone) (HIGH) | C148: 10.19 | D148: After | E148: AFTER (expected) | F148: Delete a team that owns evaluations: note where its evaluations go (today they detach and would reappear in the home list). Confirm the intended behaviour with Shawn.
A149: 10 | B149: EVALUATION SHOWS ON THE WRONG PLACES (team vs standalone) (HIGH) | C149: 10.20 | D149: After | E149: AFTER (expected) | F149: Detach an evaluation from a team (if a control exists): it returns to the home list.
A150: 10 | B150: EVALUATION SHOWS ON THE WRONG PLACES (team vs standalone) (HIGH) | C150: 10.21 | D150: After | E150: AFTER (expected) | F150: Archive a team-linked evaluation: it appears under the "Archived" view consistently (decide: archived list shows all or standalone only).
A151: 10 | B151: EVALUATION SHOWS ON THE WRONG PLACES (team vs standalone) (HIGH) | C151: 10.22 | D151: After | E151: AFTER (expected) | F151: Combine Mode: decide + verify whether team-linked evaluations can be selected; standalone ones still can.
A152: 10 | B152: EVALUATION SHOWS ON THE WRONG PLACES (team vs standalone) (HIGH) | C152: 10.23 | D152: After | E152: AFTER (expected) | F152: Free-plan EVALUATION LIMIT still counts ALL evaluations (standalone + team-linked). Creating one past the limit shows the limit message.
A153: 10 | B153: EVALUATION SHOWS ON THE WRONG PLACES (team vs standalone) (HIGH) | C153: 10.24 | D153: After | E153: AFTER (expected) | F153: "Assigned to me" (assessor) evaluations are unaffected.
A154: 10 | B154: EVALUATION SHOWS ON THE WRONG PLACES (team vs standalone) (HIGH) | C154: 10.25 | D154: After | E154: AFTER (expected) | F154: Search screen still finds team-linked evaluations.
A155: 10 | B155: EVALUATION SHOWS ON THE WRONG PLACES (team vs standalone) (HIGH) | C155: 10.26 | D155: After | E155: AFTER (expected) | F155: Organization Dashboard (org-wide reporting) totals unchanged.
A156: 10 | B156: EVALUATION SHOWS ON THE WRONG PLACES (team vs standalone) (HIGH) | C156: 10.27 | D156: After | E156: AFTER (expected) | F156: Guardian / assessor-only accounts: nothing new appears or disappears unexpectedly.
A157: 10 | B157: EVALUATION SHOWS ON THE WRONG PLACES (team vs standalone) (HIGH) | C157: 10.28 | D157: After | E157: AFTER (expected) | F157: Pull-to-refresh / app restart: lists stay correct (no evaluation flickers into the wrong list).
A158: 11 | B158: DRAG AND DROP / TRADE PLAYERS BETWEEN TEAMS ON THE APK (HIGH) | C158: 11.1 | D158: Before | E158: BEFORE (old APK - the one Shawn tested) | F158: Team Builder > Generate teams. Look for the "Adjust" button. Result: present / missing:
... A161: 11 | B161: DRAG AND DROP / TRADE PLAYERS BETWEEN TEAMS ON THE APK (HIGH) | C161: 11.4 | D161: Before | E161: BEFORE (old APK - the one Shawn tested) | F161: Note Android version, device, and navigation mode.
A162: 11 | B162: DRAG AND DROP / TRADE PLAYERS BETWEEN TEAMS ON THE APK (HIGH) | C162: 11.5 | D162: After | E162: AFTER (rebuilt APK, expected) | F162: "Adjust" button is visible after generating teams; disabled only when no split exists. | G162: Yes
A163: 11 | B163: DRAG AND DROP / TRADE PLAYERS BETWEEN TEAMS ON THE APK (HIGH) | C163: 11.6 | D163: After | E163: AFTER (rebuilt APK, expected) | F163: Adjust opens a full-screen panel with all teams + Unassigned. | G163: Yes
A164: 11 | B164: DRAG AND DROP / TRADE PLAYERS BETWEEN TEAMS ON THE APK (HIGH) | C164: 11.7 | D164: After | E164: AFTER (rebuilt APK, expected) | F164: Long-press a player (about half a second), drag onto another team -> highlights the drop target; release -> player moves. BEFORE the scroll-lock fix the same gesture scrolled the list instead (counts unchanged); AFTER it the player moved 470/471. | G164: Yes
...
